insta_meter/InstaMeter.py
insta_meter/__init__.py
insta_meter/version.py
insta_meter-0.0.2.dist-info/METADATA
insta_meter-0.0.2.dist-info/RECORD
insta_meter-0.0.2.dist-info/WHEEL
insta_meter-0.0.2.dist-info/top_level.txt
