Metadata-Version: 2.1
Name: insta-meter
Version: 0.0.2
Summary: library for gathering any instagram account statistic
Home-page: https://github.com/kricha/insta_meter
Author: Aleksej Krichevsky
Author-email: krich.al.vl@gmail.com
License: MIT
Download-URL: https://github.com/kricha/insta_meter/archive/0.0.2.tar.gz
Keywords: instagram,statistic,analytic
Platform: UNKNOWN
Classifier: Development Status :: 3 - Alpha
Classifier: License :: OSI Approved :: MIT License
Classifier: Natural Language :: English
Classifier: Programming Language :: Python
Classifier: Programming Language :: Python :: 3.6
Classifier: Topic :: Internet :: WWW/HTTP :: Browsers
Requires-Dist: tqdm
Requires-Dist: requests
